CHANGELOG.rst
LICENSE.txt
MANIFEST.in
README.rst
pyproject.toml
setup.py
batman/__init__.py
batman/openmp.py
batman/plots.py
batman/tests.py
batman/transitmodel.py
c_src/_custom_ld.c
c_src/_eclipse.c
c_src/_exponential_ld.c
c_src/_logarithmic_ld.c
c_src/_nonlinear_ld.c
c_src/_power2_ld.c
c_src/_quadratic_ld.c
c_src/_rsky.c
c_src/_uniform_ld.c
c_src/common.h
vatman_package.egg-info/PKG-INFO
vatman_package.egg-info/SOURCES.txt
vatman_package.egg-info/dependency_links.txt
vatman_package.egg-info/requires.txt
vatman_package.egg-info/top_level.txt