Metadata-Version: 1.1
Name: vatman-package
Version: 2.4.7
Summary: Fast transit light curve modeling
Home-page: https://github.com/lkreidberg/batman
Author: Laura Kreidberg
Author-email: laura.kreidberg@gmail.com
License: GNU GPLv3
Platform: UNKNOWN
Classifier: Development Status :: 5 - Production/Stable
Classifier: Intended Audience :: Science/Research
Classifier: Topic :: Scientific/Engineering
Classifier: Programming Language :: Python
